ordeq_altair/__init__.py
ordeq_altair/_version.py
ordeq_altair/chart.py
ordeq_altair/py.typed
ordeq_altair-1.0.3.dist-info/licenses/LICENSE
ordeq_altair-1.0.3.dist-info/METADATA
ordeq_altair-1.0.3.dist-info/WHEEL
ordeq_altair-1.0.3.dist-info/top_level.txt
ordeq_altair-1.0.3.dist-info/RECORD
